CONTRIBUTORS.txt
INSTALL.txt
LICENSE.txt
MANIFEST.in
README.rst
setup.py
djangoembed.egg-info/PKG-INFO
djangoembed.egg-info/SOURCES.txt
djangoembed.egg-info/dependency_links.txt
djangoembed.egg-info/top_level.txt
doc/Makefile
doc/conf.py
doc/index.rst
doc/_build/html/.buildinfo
doc/_build/html/genindex.html
doc/_build/html/index.html
doc/_build/html/objects.inv
doc/_build/html/search.html
doc/_build/html/searchindex.js
doc/_build/html/_sources/index.txt
doc/_build/html/_sources/django-oembed/getting_started.txt
doc/_build/html/_sources/django-oembed/oembed_resources.txt
doc/_build/html/_sources/django-oembed/providing_resources.txt
doc/_build/html/_sources/django-oembed/spec.txt
doc/_build/html/_sources/djangoembed/getting_started.txt
doc/_build/html/_sources/djangoembed/oembed_resources.txt
doc/_build/html/_sources/djangoembed/providing_resources.txt
doc/_build/html/_sources/djangoembed/spec.txt
doc/_build/html/_static/basic.css
doc/_build/html/_static/default.css
doc/_build/html/_static/doctools.js
doc/_build/html/_static/jquery.js
doc/_build/html/_static/pygments.css
doc/_build/html/_static/searchtools.js
doc/_build/html/django-oembed/getting_started.html
doc/_build/html/django-oembed/oembed_resources.html
doc/_build/html/django-oembed/providing_resources.html
doc/_build/html/django-oembed/spec.html
doc/_build/html/djangoembed/getting_started.html
doc/_build/html/djangoembed/oembed_resources.html
doc/_build/html/djangoembed/providing_resources.html
doc/_build/html/djangoembed/spec.html
doc/djangoembed/getting_started.rst
doc/djangoembed/oembed_resources.rst
doc/djangoembed/providing_resources.rst
doc/djangoembed/spec.rst
oembed/__init__.py
oembed/admin.py
oembed/constants.py
oembed/consumer.py
oembed/exceptions.py
oembed/fields.py
oembed/listeners.py
oembed/models.py
oembed/providers.py
oembed/resources.py
oembed/sites.py
oembed/urls.py
oembed/utils.py
oembed/views.py
oembed/fixtures/initial_data.json
oembed/image_processors/__init__.py
oembed/image_processors/pil.py
oembed/migrations/0001_initial.py
oembed/migrations/__init__.py
oembed/parsers/__init__.py
oembed/parsers/base.py
